powerindices.py
powerindices-1.0.2.dist-info/DESCRIPTION.rst
powerindices-1.0.2.dist-info/LICENSE.txt
powerindices-1.0.2.dist-info/METADATA
powerindices-1.0.2.dist-info/RECORD
powerindices-1.0.2.dist-info/WHEEL
powerindices-1.0.2.dist-info/metadata.json
powerindices-1.0.2.dist-info/top_level.txt
