Metadata-Version: 2.0
Name: powerindices
Version: 1.0.2
Summary: This package computes the following powerindices for weighted voting games: Penrose Banzhaf index, Shapley Shubik index, and Coleman Shapley index.
Home-page: https://github.com/frankhuettner/powerindices
Author: Frank Huettner
Author-email: info@frankhuettner.de
License: UNKNOWN
Project-URL: Source, https://github.com/frankhuettner/powerindices/
Keywords: Shapley value Shapley Shubik index Banzhaf Penrose Coleman Power index computation
Platform: UNKNOWN
Classifier: Development Status :: 5 - Production/Stable
Classifier: Intended Audience :: Science/Research
Classifier: Topic :: Sociology
Classifier: Topic :: Scientific/Engineering
Classifier: Topic :: Scientific/Engineering :: Mathematics
Classifier: License :: OSI Approved :: Apache Software License
Classifier: Programming Language :: Python :: 3
Classifier: Programming Language :: Python :: 3.4
Classifier: Programming Language :: Python :: 3.5
Classifier: Programming Language :: Python :: 3.6
